{
    "Ar36": {
        "error": 0.00014272841159188767,
        "error_type": "SEM",
        "filter_outliers_dict": {
            "filter_outliers": true,
            "iterations": 1,
            "std_devs": 3,
            "use_iqr_filtering": false,
            "use_standard_deviation_filtering": false
        },
        "fit": "linear",
        "fn": 338,
        "include_baseline_error": false,
        "n": 340,
        "outlier_excluded": [
            89,
            185
        ],
        "reviewed": true,
        "user_excluded": [],
        "value": 0.008280961020085317
    },
    "Ar37": {
        "error": 0.01679891494503953,
        "error_type": "SEM",
        "filter_outliers_dict": {
            "filter_outliers": true,
            "iterations": 1,
            "std_devs": 3,
            "use_iqr_filtering": false,
            "use_standard_deviation_filtering": false
        },
        "fit": "linear",
        "fn": 339,
        "include_baseline_error": false,
        "n": 340,
        "outlier_excluded": [
            51
        ],
        "reviewed": true,
        "user_excluded": [],
        "value": 1.3900880186280888
    },
    "Ar38": {
        "error": 0.00533040865859219,
        "error_type": "SEM",
        "filter_outliers_dict": {
            "filter_outliers": true,
            "iterations": 1,
            "std_devs": 3,
            "use_iqr_filtering": false,
            "use_standard_deviation_filtering": false
        },
        "fit": "linear",
        "fn": 339,
        "include_baseline_error": false,
        "n": 340,
        "outlier_excluded": [
            45
        ],
        "reviewed": true,
        "user_excluded": [],
        "value": 0.09524107912703424
    },
    "Ar39": {
        "error": 0.0083787162131397,
        "error_type": "SEM",
        "filter_outliers_dict": {
            "filter_outliers": true,
            "iterations": 1,
            "std_devs": 3,
            "use_iqr_filtering": false,
            "use_standard_deviation_filtering": false
        },
        "fit": "linear",
        "fn": 339,
        "include_baseline_error": false,
        "n": 340,
        "outlier_excluded": [
            194
        ],
        "reviewed": true,
        "user_excluded": [],
        "value": 0.0655422089118409
    },
    "Ar40": {
        "error": 0.02774385408038918,
        "error_type": "SEM",
        "filter_outliers_dict": {
            "filter_outliers": true,
            "iterations": 1,
            "std_devs": 3,
            "use_iqr_filtering": false,
            "use_standard_deviation_filtering": false
        },
        "fit": "parabolic",
        "fn": 339,
        "include_baseline_error": false,
        "n": 340,
        "outlier_excluded": [
            130
        ],
        "reviewed": true,
        "user_excluded": [],
        "value": 2.0734689066318763
    }
}