{
    "Ar36": {
        "error": 0.0051216532241169605,
        "error_type": "SEM",
        "filter_outliers_dict": {
            "filter_outliers": true,
            "iterations": 2,
            "std_devs": 2
        },
        "fit": "Parabolic",
        "value": 3.9873293777489414
    },
    "Ar37": {
        "error": 0.01433267674251409,
        "error_type": "SEM",
        "filter_outliers_dict": {
            "filter_outliers": true,
            "iterations": 2,
            "std_devs": 2
        },
        "fit": "linear",
        "value": 5.813559987815289
    },
    "Ar38": {
        "error": 0.004936112821985936,
        "error_type": "SEM",
        "filter_outliers_dict": {
            "filter_outliers": true,
            "iterations": 2,
            "std_devs": 2
        },
        "fit": "linear",
        "value": 1.167603679143336
    },
    "Ar39": {
        "error": 0.015717076126043086,
        "error_type": "SEM",
        "filter_outliers_dict": {
            "filter_outliers": true,
            "iterations": 2,
            "std_devs": 2
        },
        "fit": "Parabolic",
        "value": 20.539303824782714
    },
    "Ar40": {
        "error": 0.10048858105835498,
        "error_type": "SEM",
        "filter_outliers_dict": {
            "filter_outliers": true,
            "iterations": 2,
            "std_devs": 2
        },
        "fit": "Parabolic",
        "value": 1255.9452135200424
    }
}